langchain_daytona_data_analysis/__init__.py
langchain_daytona_data_analysis/py.typed
langchain_daytona_data_analysis/tools.py
langchain_daytona_data_analysis/unparse.py
langchain_daytona_data_analysis-0.1.1.dist-info/METADATA
langchain_daytona_data_analysis-0.1.1.dist-info/WHEEL
langchain_daytona_data_analysis-0.1.1.dist-info/licenses/LICENSE
langchain_daytona_data_analysis-0.1.1.dist-info/RECORD
