Metadata-Version: 2.4
Name: langchain-daytona-data-analysis
Version: 0.1.1
Summary: An integration package connecting DaytonaDataAnalysis and LangChain
License: MIT
License-File: LICENSE
Requires-Python: >=3.9,<4.0
Classifier: License :: OSI Approved :: MIT License
Classifier: Programming Language :: Python :: 3
Classifier: Programming Language :: Python :: 3.9
Classifier: Programming Language :: Python :: 3.10
Classifier: Programming Language :: Python :: 3.11
Classifier: Programming Language :: Python :: 3.12
Classifier: Programming Language :: Python :: 3.13
Classifier: Programming Language :: Python :: 3.14
Requires-Dist: daytona (>=0.113.2,<0.114.0)
Requires-Dist: langchain-core (>=0.3.15,<2.0.0)
Project-URL: Repository, https://github.com/daytonaio/langchain_daytona_data_analysis
Project-URL: Release Notes, https://github.com/daytonaio/langchain_daytona_data_analysis/releases
Project-URL: Source Code, https://github.com/daytonaio/langchain_daytona_data_analysis
